bitpapa_pay/__init__.py
bitpapa_pay/client.py
bitpapa_pay/enums/__init__.py
bitpapa_pay/enums/crypto_currency_code.py
bitpapa_pay/enums/invoice_type.py
bitpapa_pay/enums/paid_button_type.py
bitpapa_pay/enums/request_type.py
bitpapa_pay/exceptions.py
bitpapa_pay/methods/__init__.py
bitpapa_pay/methods/addresses.py
bitpapa_pay/methods/base.py
bitpapa_pay/methods/default.py
bitpapa_pay/methods/invoices.py
bitpapa_pay/methods/transactions.py
bitpapa_pay/schemas/__init__.py
bitpapa_pay/schemas/addresses.py
bitpapa_pay/schemas/default.py
bitpapa_pay/schemas/invoices.py
bitpapa_pay/schemas/transactions.py
bitpapa_pay-0.2.4.dist-info/METADATA
bitpapa_pay-0.2.4.dist-info/WHEEL
bitpapa_pay-0.2.4.dist-info/RECORD
